context_extension/__init__.py
context_extension/benchmark_model.py
context_extension/interpolate_embeddings.py
context_extension-0.1.3.dist-info/licenses/LICENSE
context_extension-0.1.3.dist-info/licenses/NOTICE
context_extension-0.1.3.dist-info/METADATA
context_extension-0.1.3.dist-info/WHEEL
context_extension-0.1.3.dist-info/entry_points.txt
context_extension-0.1.3.dist-info/top_level.txt
context_extension-0.1.3.dist-info/RECORD
