Metadata-Version: 2.4
Name: context-extension
Version: 0.1.3
Summary: Zero-Training Context Extension for Transformer Encoders via Nonlinear Absolute Positional Embeddings Interpolation
Author-email: Ivan Danylenko <kowd.pauuh@gmail.com>
License: Apache-2.0
Project-URL: Homepage, https://github.com/Kowd-PauUh
Project-URL: Repository, https://github.com/Kowd-PauUh/encoders-context-extension
Keywords: sentence transformers,context extension
Classifier: Development Status :: 4 - Beta
Classifier: Intended Audience :: Developers
Classifier: Intended Audience :: Education
Classifier: Intended Audience :: Science/Research
Classifier: License :: OSI Approved :: Apache Software License
Classifier: Programming Language :: Python :: 3
Classifier: Programming Language :: Python :: 3.10
Classifier: Programming Language :: Python :: 3.11
Classifier: Programming Language :: Python :: 3.12
Classifier: Programming Language :: Python :: 3.13
Classifier: Topic :: Scientific/Engineering
Classifier: Topic :: Scientific/Engineering :: Artificial Intelligence
Classifier: Topic :: Software Development
Classifier: Topic :: Software Development :: Libraries
Classifier: Topic :: Software Development :: Libraries :: Python Modules
Requires-Python: >=3.10
License-File: LICENSE
License-File: NOTICE
Requires-Dist: torch
Requires-Dist: sentence-transformers
Requires-Dist: scipy
Dynamic: license-file
